aepsicro
