Metadata-Version: 1.1
Name: aepsicro
Version: 0.0.6
Summary: Psicrometría / Psychrometrics
Home-page: https://pypi.python.org/pypi/aepsicro
Author: Antonio Eduardo Téllez Santos
Author-email: aironmail@gmail.com
License: GNU GPLv3
Keywords: psychrometrics,psicrometría
Platform: UNKNOWN
Classifier: Development Status :: 3 - Alpha
Classifier: Intended Audience :: Science/Research
Classifier: Intended Audience :: Developers
Classifier: Programming Language :: Python
Classifier: Programming Language :: Python :: 3.3
Classifier: Programming Language :: Python :: 3.4
Classifier: Programming Language :: Python :: 3.5
Classifier: Topic :: Scientific/Engineering
Classifier: License :: OSI Approved :: GNU General Public License v3 (GPLv3)
